MANIFEST.in
README.md
setup.py
extended_rospylogs/__init__.py
extended_rospylogs.egg-info/PKG-INFO
extended_rospylogs.egg-info/SOURCES.txt
extended_rospylogs.egg-info/dependency_links.txt
extended_rospylogs.egg-info/top_level.txt