Metadata-Version: 1.0
Name: extended-rospylogs
Version: 0.0.5
Summary: Extension of logs for rospy based con roscpp.
Home-page: https://github.com/charlielito/extended_rospylogs
Author: Carlos Alvarez
Author-email: candres.alv@gmail.com
License: MIT
Platform: UNKNOWN
